cdediff/__init__.py
cdediff/data.py
cdediff/difftool.py
cdediff/output.py
cdediff/setup_gitdiff.py
cdediff/textconv.py
cdediff/util.py
cdediff-1.0.0.dist-info/LICENSE
cdediff-1.0.0.dist-info/METADATA
cdediff-1.0.0.dist-info/WHEEL
cdediff-1.0.0.dist-info/top_level.txt
cdediff-1.0.0.dist-info/RECORD
