Metadata-Version: 2.1
Name: cdediff
Version: 1.0.0
Summary: Creates human readable descriptions and comparisons of CdEDB-Events.
Author-email: Tobias Udtke <tobias.udtke@gmail.com>
Classifier: Programming Language :: Python :: 3
Classifier: Programming Language :: Python :: 3.10
Classifier: License :: OSI Approved :: GNU General Public License (GPL)
Classifier: Operating System :: OS Independent
Requires-Python: >=3.10
License-File: LICENSE
Requires-Dist: termcolor ~=2.4.0
